xm_agent/__init__.py
xm_agent/config.py
xm_agent/download.py
xm_agent/generate.py
xm_agent/hash.py
xm_agent/metadata.py
xm_agent/models.py
xm_agent/sd_install.py
xm_agent/server.py
xm_agent/tasks.py
xm_agent-0.1.13.dist-info/WHEEL
xm_agent-0.1.13.dist-info/entry_points.txt
xm_agent-0.1.13.dist-info/METADATA
xm_agent-0.1.13.dist-info/RECORD
