Metadata-Version: 2.3
Name: xm-agent
Version: 0.1.13
Summary: HTTP API agent for remote model management
Author: Adam Ladachowski
Author-email: Adam Ladachowski <adam.ladachowski@gmail.com>
Requires-Dist: fastapi>=0.115.0
Requires-Dist: uvicorn[standard]>=0.34.0
Requires-Dist: httpx>=0.28.0
Requires-Dist: pydantic-settings>=2.7.0
Requires-Dist: pytest>=8.0.0 ; extra == 'dev'
Requires-Dist: pytest-asyncio>=0.25.0 ; extra == 'dev'
Requires-Python: >=3.12
Provides-Extra: dev
